poetry_plugin_sort/__init__.py
poetry_plugin_sort/config.py
poetry_plugin_sort/plugins.py
poetry_plugin_sort/sort.py
poetry_plugin_sort/utils.py
poetry_plugin_sort-0.2.2.dist-info/LICENSE
poetry_plugin_sort-0.2.2.dist-info/METADATA
poetry_plugin_sort-0.2.2.dist-info/WHEEL
poetry_plugin_sort-0.2.2.dist-info/entry_points.txt
poetry_plugin_sort-0.2.2.dist-info/RECORD
