Metadata-Version: 2.3
Name: poetry-plugin-sort
Version: 0.2.2
Summary: Poetry plugin to sort the dependencies alphabetically
Home-page: https://github.com/andrei-shabanski/poetry-plugin-sort
License: MIT
Keywords: poetry,plugin,dependencies sorting
Author: Andrei Shabanski
Author-email: shabanski.andrei@gmail.com
Requires-Python: >=3.8,<4.0
Classifier: License :: OSI Approved :: MIT License
Classifier: Programming Language :: Python :: 3
Classifier: Programming Language :: Python :: 3.8
Classifier: Programming Language :: Python :: 3.9
Classifier: Programming Language :: Python :: 3.10
Classifier: Programming Language :: Python :: 3.11
Classifier: Programming Language :: Python :: 3.12
Classifier: Programming Language :: Python :: 3.13
Requires-Dist: poetry (>=1.2)
Project-URL: Repository, https://github.com/andrei-shabanski/poetry-plugin-sort
